README
setup.py
bamboo/__init__.py
bamboo.setuptools_version.egg-info/PKG-INFO
bamboo.setuptools_version.egg-info/SOURCES.txt
bamboo.setuptools_version.egg-info/dependency_links.txt
bamboo.setuptools_version.egg-info/namespace_packages.txt
bamboo.setuptools_version.egg-info/top_level.txt
bamboo/setuptools_version/__init__.py
bamboo/setuptools_version/versionlib.py