Metadata-Version: 1.0
Name: bamboo.setuptools-version
Version: 0.0.1
Summary: Tiny package to dop just one things -0 solve gettng a vfersion number for a package
Home-page: https://github.com/Connexions/bamboo.setuptools_version
Author: See AUTHORS.txt
Author-email: info@cnx.org
License: LICENSE.txt
Platform: UNKNOWN
